stdcomLabjack/Labjack
stdcomLabjack/__init__.py
stdcomLabjack/labjacku6gui.py
stdcomLabjack/labjacku6gui.ui
stdcomLabjack/stecLabjack.py
stdcomLabjack/u6Noise.py
stdcomLabjack/u6allio.py
stdcomLabjack/__pycache__/labjacku6gui.cpython-310.pyc
stdcomLabjack/__pycache__/u6allio.cpython-310.pyc
stdcomLabjack/html/stdcomLabjack.html
stdcomLabjack/html/stdcomLabjack.odt
stdcomQtPiPlate/Stec.PJanice
stdcomQtPiPlate/showHelp.py
stdcomQtPiPlate/stdcomQtPiPlateADC.py
stdcomQtPiPlate/stdcomQtpi.py
stdcomQtPiPlate/stdcomQtpi.ui
stdcomQtPiPlate/__pycache__/showHelp.cpython-310.pyc
stdcomQtPiPlate/__pycache__/stdcomQtpi.cpython-310.pyc
stdcomQtPiPlate/html/ADCplate Users Guide – Pi-Plates.pdf
stdcomQtPiPlate/html/ADCplate-12_1.png
stdcomQtPiPlate/html/ADCplate-14_1.png
stdcomQtPiPlate/html/ADCplate-1_1.png
stdcomQtPiPlate/html/ADCplate-1_2.png
stdcomQtPiPlate/html/ADCplate-1_3.png
stdcomQtPiPlate/html/ADCplate-1_4.png
stdcomQtPiPlate/html/ADCplate-1_5.png
stdcomQtPiPlate/html/ADCplate-2_1.png
stdcomQtPiPlate/html/ADCplate-2_2.png
stdcomQtPiPlate/html/ADCplate-6_1.png
stdcomQtPiPlate/html/ADCplate_ind.html
stdcomQtPiPlate/html/ADCplates.html
stdcomQt_pi-2.0.1.dist-info/LICENSE.txt
stdcomQt_pi-2.0.1.dist-info/METADATA
stdcomQt_pi-2.0.1.dist-info/WHEEL
stdcomQt_pi-2.0.1.dist-info/top_level.txt
stdcomQt_pi-2.0.1.dist-info/RECORD
